scrapli_ipython/__init__.py
scrapli_ipython/scrapli_ipython.py
scrapli_ipython-0.0.9.dist-info/LICENSE
scrapli_ipython-0.0.9.dist-info/METADATA
scrapli_ipython-0.0.9.dist-info/WHEEL
scrapli_ipython-0.0.9.dist-info/top_level.txt
scrapli_ipython-0.0.9.dist-info/RECORD
