Metadata-Version: 2.1
Name: scrapli-ipython
Version: 0.0.9
Summary: scrapli extention for ipython
Home-page: https://github.com/haccht/scrapli_ipython
Author: haccht
Requires-Python: >=3.8
License-File: LICENSE
Requires-Dist: scrapli[ssh2]
Requires-Dist: ntc-templates
Requires-Dist: jinja2
Requires-Dist: ipython
